azure/mgmt/kusto/__init__.py
azure/mgmt/kusto/_configuration.py
azure/mgmt/kusto/_kusto_management_client.py
azure/mgmt/kusto/_patch.py
azure/mgmt/kusto/_serialization.py
azure/mgmt/kusto/_version.py
azure/mgmt/kusto/py.typed
azure/mgmt/kusto/aio/__init__.py
azure/mgmt/kusto/aio/_configuration.py
azure/mgmt/kusto/aio/_kusto_management_client.py
azure/mgmt/kusto/aio/_patch.py
azure/mgmt/kusto/aio/operations/__init__.py
azure/mgmt/kusto/aio/operations/_attached_database_configurations_operations.py
azure/mgmt/kusto/aio/operations/_cluster_principal_assignments_operations.py
azure/mgmt/kusto/aio/operations/_clusters_operations.py
azure/mgmt/kusto/aio/operations/_data_connections_operations.py
azure/mgmt/kusto/aio/operations/_database_operations.py
azure/mgmt/kusto/aio/operations/_database_principal_assignments_operations.py
azure/mgmt/kusto/aio/operations/_databases_operations.py
azure/mgmt/kusto/aio/operations/_managed_private_endpoints_operations.py
azure/mgmt/kusto/aio/operations/_operations.py
azure/mgmt/kusto/aio/operations/_operations_results_location_operations.py
azure/mgmt/kusto/aio/operations/_operations_results_operations.py
azure/mgmt/kusto/aio/operations/_patch.py
azure/mgmt/kusto/aio/operations/_private_endpoint_connections_operations.py
azure/mgmt/kusto/aio/operations/_private_link_resources_operations.py
azure/mgmt/kusto/aio/operations/_sandbox_custom_images_operations.py
azure/mgmt/kusto/aio/operations/_scripts_operations.py
azure/mgmt/kusto/aio/operations/_skus_operations.py
azure/mgmt/kusto/models/__init__.py
azure/mgmt/kusto/models/_kusto_management_client_enums.py
azure/mgmt/kusto/models/_models_py3.py
azure/mgmt/kusto/models/_patch.py
azure/mgmt/kusto/operations/__init__.py
azure/mgmt/kusto/operations/_attached_database_configurations_operations.py
azure/mgmt/kusto/operations/_cluster_principal_assignments_operations.py
azure/mgmt/kusto/operations/_clusters_operations.py
azure/mgmt/kusto/operations/_data_connections_operations.py
azure_mgmt_kusto-3.4.0.dist-info/LICENSE
azure_mgmt_kusto-3.4.0.dist-info/METADATA
azure_mgmt_kusto-3.4.0.dist-info/WHEEL
azure_mgmt_kusto-3.4.0.dist-info/top_level.txt
azure_mgmt_kusto-3.4.0.dist-info/RECORD
